hf_transfer.so
scoamp/__init__.py
scoamp/api.py
scoamp/commands/__init__.py
scoamp/commands/api.py
scoamp/commands/internal/__init__.py
scoamp/commands/internal/env.py
scoamp/commands/internal/public_model.py
scoamp/commands/lfs.py
scoamp/commands/main.py
scoamp/globals.py
scoamp/schema/public-model-meta.json
scoamp/toolkit.py
scoamp/utils/__init__.py
scoamp/utils/api_utils.py
scoamp/utils/decrypt.py
scoamp/utils/error.py
scoamp/utils/helper.py
scoamp/utils/logger.py
scoamp/version.py
scoamppro-0.6.10.dist-info/WHEEL
scoamppro-0.6.10.dist-info/METADATA
scoamppro-0.6.10.dist-info/entry_points.txt
scoamppro-0.6.10.dist-info/RECORD
