Metadata-Version: 2.1
Name: scoamppro
License: Apache 2.0
Summary: SenseCore AI Model Platform Command Line Tool
Classifier: License :: OSI Approved :: Apache Software License
Classifier: Operating System :: OS Independent
Classifier: Programming Language :: Python :: 3
Classifier: Programming Language :: Python :: 3 :: Only
Classifier: Programming Language :: Python :: 3.9
Classifier: Programming Language :: Python :: 3.10
Classifier: Programming Language :: Python :: 3.11
Classifier: Topic :: Scientific/Engineering :: Artificial Intelligence
Requires-Python: >=3.9
Requires-Dist: requests
Requires-Dist: rich
Requires-Dist: filelock
Requires-Dist: tqdm
Requires-Dist: pycryptodome
Requires-Dist: typer==0.7.0
Requires-Dist: click==8.1.7
Requires-Dist: jsonschema>=3.2
Version: 0.6.10
